stixmarx/__init__.py
stixmarx/attrmap.py
stixmarx/container.py
stixmarx/errors.py
stixmarx/markingmap.py
stixmarx/navigator.py
stixmarx/parser.py
stixmarx/serializer.py
stixmarx/utils.py
stixmarx/version.py
stixmarx/xml.py
stixmarx/api/__init__.py
stixmarx/api/types.py
stixmarx/fields/__init__.py
stixmarx-1.0.8.dist-info/LICENSE.txt
stixmarx-1.0.8.dist-info/METADATA
stixmarx-1.0.8.dist-info/WHEEL
stixmarx-1.0.8.dist-info/top_level.txt
stixmarx-1.0.8.dist-info/RECORD
